.gitignore
.gitmodules
CMakeLists.txt
CMakeLists.txt.gtest.in
LICENSE
MANIFEST.in
README.md
README.pypi
appveyor.yml
requirements.txt
setup.cfg
setup.py
test-requirements.txt
versioneer.py
.circleci/config.yml
CMakeFiles/CMakeError.log
CMakeFiles/CMakeOutput.log
CMakeFiles/3.20.2/CMakeCCompiler.cmake
CMakeFiles/3.20.2/CMakeCXXCompiler.cmake
CMakeFiles/3.20.2/CMakeDetermineCompilerABI_C.bin
CMakeFiles/3.20.2/CMakeDetermineCompilerABI_CXX.bin
CMakeFiles/3.20.2/CMakeSystem.cmake
CMakeFiles/3.20.2/CompilerIdC/CMakeCCompilerId.c
CMakeFiles/3.20.2/CompilerIdCXX/CMakeCXXCompilerId.cpp
deps/xmr-stak/.appveyor.yml
deps/xmr-stak/.git
deps/xmr-stak/.gitattributes
deps/xmr-stak/.gitignore
deps/xmr-stak/.travis.yml
deps/xmr-stak/CMakeLists.txt
deps/xmr-stak/CONTRIBUTING.md
deps/xmr-stak/Dockerfile
deps/xmr-stak/LICENSE
deps/xmr-stak/README.md
deps/xmr-stak/THIRD-PARTY-LICENSES
deps/xmr-stak/.github/ISSUE_TEMPLATE.md
deps/xmr-stak/.github/PULL_REQUEST_TEMPLATE.md
deps/xmr-stak/CI/checkPRBranch
deps/xmr-stak/doc/FAQ.md
deps/xmr-stak/doc/compile.md
deps/xmr-stak/doc/compile_FreeBSD.md
deps/xmr-stak/doc/compile_Linux.md
deps/xmr-stak/doc/compile_Windows.md
deps/xmr-stak/doc/compile_macOS.md
deps/xmr-stak/doc/pgp_keys.md
deps/xmr-stak/doc/tuning.md
deps/xmr-stak/doc/usage.md
deps/xmr-stak/scripts/build_xmr-stak_docker/build_xmr-stak_docker.sh
deps/xmr-stak/xmrstak/config.tpl
deps/xmr-stak/xmrstak/donate-level.hpp
deps/xmr-stak/xmrstak/jconf.cpp
deps/xmr-stak/xmrstak/jconf.hpp
deps/xmr-stak/xmrstak/params.hpp
deps/xmr-stak/xmrstak/pools.tpl
deps/xmr-stak/xmrstak/version.cpp
deps/xmr-stak/xmrstak/version.hpp
deps/xmr-stak/xmrstak/backend/backendConnector.cpp
deps/xmr-stak/xmrstak/backend/backendConnector.hpp
deps/xmr-stak/xmrstak/backend/cryptonight.hpp
deps/xmr-stak/xmrstak/backend/globalStates.cpp
deps/xmr-stak/xmrstak/backend/globalStates.hpp
deps/xmr-stak/xmrstak/backend/iBackend.hpp
deps/xmr-stak/xmrstak/backend/miner_work.hpp
deps/xmr-stak/xmrstak/backend/plugin.hpp
pyqryptonight.egg-info/PKG-INFO
pyqryptonight.egg-info/SOURCES.txt
pyqryptonight.egg-info/dependency_links.txt
pyqryptonight.egg-info/top_level.txt
