Metadata-Version: 1.1
Name: pyqryptonight
Version: 0.99.11
Summary: QRL cryptonight library
Home-page: http://theqrl.org
Author: The Quantum Resistant Ledger
Author-email: info@theQRL.org
License: GPL3
Platform: UNKNOWN
Classifier: Development Status :: 3 - Alpha
Classifier: Programming Language :: Python
Classifier: Programming Language :: Python :: 3
Classifier: Programming Language :: Python :: 3.5
